django_constance_register-0.2.0.dist-info/dependency_links.txt
django_constance_register-0.2.0.dist-info/entry_points.txt
django_constance_register-0.2.0.dist-info/METADATA
django_constance_register-0.2.0.dist-info/top_level.txt
django_constance_register-0.2.0.dist-info/WHEEL
setup.py
__init__.py
constance_register/apps.py
constance_register/conf.py
constance_register/__init__.py
example/library/settings.py
example/library/urls.py
example/library/wsgi.py
example/library/__init__.py
example/library/apps/__init__.py
example/library/apps/shelf/config.py
example/library/apps/shelf/models.py
example/library/apps/shelf/__init__.py
example/library/apps/shelf/migrations/0001_initial.py
example/library/apps/shelf/migrations/__init__.py
example/library/apps/staff/admin.py
example/library/apps/staff/config.py
example/library/apps/staff/models.py
example/library/apps/staff/__init__.py
example/library/apps/staff/migrations/0001_initial.py
example/library/apps/staff/migrations/__init__.py
poetry.lock
README.rst
README.md
django_constance_register.egg-info/dependency_links.txt
django_constance_register.egg-info/entry_points.txt
django_constance_register.egg-info/requires.txt
django_constance_register.egg-info/SOURCES.txt
django_constance_register.egg-info/top_level.txt
pyproject.toml
django_constance_register-0.2.0.dist-info/RECORD