Metadata-Version: 2.1
Name: django-constance-register
Version: 0.2.0
Summary: Per app constance settings
Project-URL: Repository, https://gitlab.com/cyberbudy/django-constance-register
Author: cyberbudy
Author-email: cyberbudy@gmail.com
License: MIT
Requires-Python: >=3.6
Classifier: Development Status :: 4 - Beta
Classifier: Programming Language :: Python :: 3
Classifier: Framework :: Django
Classifier: Intended Audience :: Developers
Classifier: Topic :: Utilities
Classifier: License :: OSI Approved :: MIT License
Classifier: Operating System :: OS Independent
Requires-Dist: django>=3.0.0
Requires-Dist: django-constance>=2.8.0
Requires-Dist: django-picklefield==3.*,>=3.0.1; extra == "dev"
Requires-Dist: python-memcached==1.*,>=1.59.0; extra == "dev"
Requires-Dist: redis==3.*,>=3.5.3; extra == "dev"
Provides-Extra: dev
